setup.py
wizards/__init__.py
wizards/codec.py
wizards/errors.py
wizards/services.py
wizards.egg-info/PKG-INFO
wizards.egg-info/SOURCES.txt
wizards.egg-info/dependency_links.txt
wizards.egg-info/requires.txt
wizards.egg-info/top_level.txt
wizards/config/__init__.py
wizards/error/__init__.py
wizards/storage/__init__.py
wizards/storage/engine.py
wizards/storage/repository.py
wizards/storage/session.py
wizards/testing/__init__.py
wizards/testing/base.py
wizards/testing/ctrl.py
wizards/testing/endpoint.py
wizards/testing/system.py
wizards/wsgi/__init__.py
wizards/wsgi/application.py
wizards/wsgi/authenticator.py
wizards/wsgi/ctrl.py
wizards/wsgi/decorators.py
wizards/wsgi/exc.py
wizards/wsgi/handler.py
wizards/wsgi/payload.py
wizards/wsgi/request.py
wizards/wsgi/response.py
wizards/wsgi/endpoint/__init__.py
wizards/wsgi/endpoint/base.py
wizards/wsgi/endpoint/provider.py