Metadata-Version: 1.0
Name: wizards
Version: 1.2.2
Summary: Wizards of Industry Common Library
Home-page: https://www.wizardsofindustry.net
Author: Cochise Ruhulessin
Author-email: cochiseruhulessin@gmail.com
License: UNKNOWN
Platform: UNKNOWN
